src/__init__.py
src/main.py
pypeermap-0.0.1.1.dist-info/METADATA
pypeermap-0.0.1.1.dist-info/WHEEL
pypeermap-0.0.1.1.dist-info/entry_points.txt
pypeermap-0.0.1.1.dist-info/license_files/LICENSE
pypeermap-0.0.1.1.dist-info/RECORD
