Metadata-Version: 2.1
Name: pypeermap
Version: 0.0.1.1
Summary: pypeermap is a simple python tool for obtaining all the IP addresses on your local network. 
Project-URL: Bug Tracker, https://github.com/pypa/sampleproject/issues
Project-URL: Homepage, https://github.com/pypa/sampleproject
Author-email: Naseem Alsadi <nalsadi01@gmail.com>
License: MIT License
Classifier: License :: OSI Approved :: MIT License
Classifier: Operating System :: OS Independent
Classifier: Programming Language :: Python :: 3
Requires-Python: >=3.7
